mockdata/__init__.py
mockdata/init.py
mockdata/fields/__init__.py
mockdata/fields/mock_address.py
mockdata/fields/mock_automotive.py
mockdata/fields/mock_bank.py
mockdata/fields/mock_color.py
mockdata/fields/mock_company.py
mockdata/fields/mock_credit_card.py
mockdata/fields/mock_currency.py
mockdata/fields/mock_emoji.py
mockdata/fields/mock_file.py
mockdata/fields/mock_geo.py
mockdata/fields/mock_internet.py
mockdata/fields/mock_job.py
mockdata/fields/mock_lorem.py
mockdata/fields/mock_misc.py
mockdata/fields/mock_passport.py
mockdata/fields/mock_person.py
mockdata/fields/mock_phone.py
mockdata/fields/mock_profile.py
mockdata/fields/mock_python.py
mockdata/fields/mock_ssn.py
mockdata/fields/mock_time.py
mockdata/fields/mock_user_agent.py
mockdata/utils/__init__.py
mockdata/utils/convert.py
mockdata-1.0.3.dist-info/METADATA
mockdata-1.0.3.dist-info/WHEEL
mockdata-1.0.3.dist-info/top_level.txt
mockdata-1.0.3.dist-info/RECORD
