Metadata-Version: 2.1
Name: mockdata
Version: 1.0.3
Summary: mockdata生产数据
Home-page: https://github.com/Joyamon/mockdata
Author: 半只程序员
Classifier: Programming Language :: Python :: 3 :: Only
Classifier: Programming Language :: Python :: 3.7
Classifier: Programming Language :: Python :: 3.8
Classifier: Programming Language :: Python :: 3.9
Classifier: Programming Language :: Python :: 3.10
Classifier: Programming Language :: Python :: 3.11
Classifier: Programming Language :: Python :: 3.12
Classifier: License :: OSI Approved :: MIT License
Classifier: Operating System :: OS Independent
Requires-Python: <3.13
Requires-Dist: Faker
Requires-Dist: Pillow
